everythingjs/__init__.py
everythingjs/app.py
everythingjs/__pycache__/app.cpython-313.pyc
everythingjs/templates/monitor.html
everythingjs/templates/template.html
everythingjs-0.2.6.dist-info/METADATA
everythingjs-0.2.6.dist-info/WHEEL
everythingjs-0.2.6.dist-info/entry_points.txt
everythingjs-0.2.6.dist-info/top_level.txt
everythingjs-0.2.6.dist-info/RECORD
