Metadata-Version: 2.1
Name: everythingjs
Version: 0.2.6
Summary: A Python module for working seamlessly with JavaScript files.
Home-page: https://github.com/profmoriarity/everythingjs
Author: Siva Krishna
Author-email: krishna.krish759213@gmail.com
Classifier: Development Status :: 4 - Beta
Classifier: Intended Audience :: Developers
Classifier: Programming Language :: Python :: 3
Classifier: License :: OSI Approved :: MIT License
Classifier: Operating System :: OS Independent
Requires-Python: >=3.6
Requires-Dist: beautifulsoup4
Requires-Dist: requests
Requires-Dist: tqdm
Requires-Dist: flask
Requires-Dist: jsbeautifier
Requires-Dist: flask-socketio
